funtecplot/__init__.py
funtecplot/dump/__init__.py
funtecplot/dump/base.py
funtecplot/dump/point.py
funtecplot/dump/triangle.py
funtecplot-1.0.3.dist-info/METADATA
funtecplot-1.0.3.dist-info/WHEEL
funtecplot-1.0.3.dist-info/top_level.txt
funtecplot-1.0.3.dist-info/RECORD
