Metadata-Version: 2.2
Name: funtecplot
Version: 1.0.3
Summary: funtecplot
Author-email: niuliangtao <farfarfun@qq.com>
Requires-Python: >=3.7
